LICENSE
README.md
setup.py
NamedEntityRecognition/AutoNER.c
NamedEntityRecognition/AutoNER.pxd
NamedEntityRecognition/AutoNER.pyx
NamedEntityRecognition/Gazetteer.c
NamedEntityRecognition/Gazetteer.pxd
NamedEntityRecognition/Gazetteer.pyx
NamedEntityRecognition/NERCorpus.c
NamedEntityRecognition/NERCorpus.pxd
NamedEntityRecognition/NERCorpus.pyx
NamedEntityRecognition/NamedEntitySentence.c
NamedEntityRecognition/NamedEntitySentence.pxd
NamedEntityRecognition/NamedEntitySentence.pyx
NamedEntityRecognition/NamedEntityType.py
NamedEntityRecognition/NamedEntityWord.c
NamedEntityRecognition/NamedEntityWord.pxd
NamedEntityRecognition/NamedEntityWord.pyx
NamedEntityRecognition/Slot.c
NamedEntityRecognition/Slot.pxd
NamedEntityRecognition/Slot.pyx
NamedEntityRecognition/SlotType.py
NamedEntityRecognition/__init__.py
NamedEntityRecognition/data/__init__.py
NamedEntityRecognition/data/gazetteer-location.txt
NamedEntityRecognition/data/gazetteer-organization.txt
NamedEntityRecognition/data/gazetteer-person.txt
NlpToolkit_NamedEntityRecognition_Cy.egg-info/PKG-INFO
NlpToolkit_NamedEntityRecognition_Cy.egg-info/SOURCES.txt
NlpToolkit_NamedEntityRecognition_Cy.egg-info/dependency_links.txt
NlpToolkit_NamedEntityRecognition_Cy.egg-info/requires.txt
NlpToolkit_NamedEntityRecognition_Cy.egg-info/top_level.txt
nlptoolkit_namedentityrecognition_cy.egg-info/PKG-INFO
nlptoolkit_namedentityrecognition_cy.egg-info/SOURCES.txt
nlptoolkit_namedentityrecognition_cy.egg-info/dependency_links.txt
nlptoolkit_namedentityrecognition_cy.egg-info/requires.txt
nlptoolkit_namedentityrecognition_cy.egg-info/top_level.txt