Metadata-Version: 2.4
Name: nlptoolkit-namedentityrecognition-cy
Version: 1.0.10
Summary: NER Corpus Processing Library
Home-page: https://github.com/StarlangSoftware/TurkishNamedEntityRecognition-Cy
Author: olcaytaner
Author-email: olcay.yildiz@ozyegin.edu.tr
License-File: LICENSE
Requires-Dist: NlpToolkit-Corpus-Cy
Dynamic: author
Dynamic: author-email
Dynamic: description
Dynamic: description-content-type
Dynamic: home-page
Dynamic: license-file
Dynamic: requires-dist
Dynamic: summary
